{"annotation":[{"shape":"circle","color":"red","kind":"normal","box":[1655,408,1691,447],"text":"0","type":"restriction","class":"traffic_sign"},{"shape":"rectangle","color":"blue","kind":"normal","box":[1603,468,1619,489],"text":"0","type":"instruction","class":"traffic_sign"},{"shape":"rectangle","color":"blue","kind":"normal","box":[1430,254,1503,342],"text":"0","type":"instruction","class":"traffic_sign"},{"shape":"circle","color":"blue","kind":"normal","box":[1223,211,1271,259],"text":"0","type":"instruction","class":"traffic_sign"},{"shape":"rectangle","color":"blue","kind":"normal","box":[553,435,568,451],"text":"0","type":"instruction","class":"traffic_sign"},{"light_count":"4","box":[1117,258,1194,289],"attribute":[{"red":"off","green":"on","x_light":"off","others_arrow":"off","yellow":"off","left_arrow":"off"}],"type":"car","class":"traffic_light","direction":"horizontal"},{"light_count":"4","box":[1313,259,1395,282],"attribute":[{"red":"off","green":"on","x_light":"off","others_arrow":"off","yellow":"off","left_arrow":"off"}],"type":"car","class":"traffic_light","direction":"horizontal"},{"light_count":"4","box":[1505,250,1592,282],"attribute":[{"red":"off","green":"on","x_light":"off","others_arrow":"off","yellow":"off","left_arrow":"off"}],"type":"car","class":"traffic_light","direction":"horizontal"}],"image":{"filename":"13679854.jpg","imsize":[1920,1080]}}