{"annotation":[{"light_count":"2","box":[1121,366,1155,424],"attribute":[{"red":"off","green":"off","x_light":"off","others_arrow":"off","yellow":"off","left_arrow":"off"}],"type":"pedestrian","class":"traffic_light","direction":"vertical"},{"light_count":"4","box":[1673,163,1759,208],"attribute":[{"red":"on","green":"off","x_light":"off","others_arrow":"off","yellow":"off","left_arrow":"off"}],"type":"car","class":"traffic_light","direction":"horizontal"},{"light_count":"4","box":[1852,137,1920,193],"attribute":[{"red":"on","green":"off","x_light":"off","others_arrow":"off","yellow":"off","left_arrow":"off"}],"type":"car","class":"traffic_light","direction":"horizontal"}],"image":{"filename":"13729997.jpg","imsize":[1920,1080]}}