{"annotation":[{"light_count":"4","box":[1621,401,1630,406],"attribute":[{"red":"off","green":"on","x_light":"off","others_arrow":"off","yellow":"off","left_arrow":"off"}],"type":"car","class":"traffic_light","direction":"horizontal"},{"light_count":"4","box":[1767,390,1777,395],"attribute":[{"red":"off","green":"on","x_light":"off","others_arrow":"off","yellow":"off","left_arrow":"off"}],"type":"car","class":"traffic_light","direction":"horizontal"},{"light_count":"4","box":[1809,385,1818,390],"attribute":[{"red":"off","green":"on","x_light":"off","others_arrow":"off","yellow":"off","left_arrow":"off"}],"type":"car","class":"traffic_light","direction":"horizontal"}],"image":{"filename":"14677457.jpg","imsize":[1920,1080]}}