{"annotation":[{"shape":"triangle","color":"blue","kind":"normal","box":[572,591,598,625],"text":"0","type":"instruction","class":"traffic_sign"},{"shape":"rectangle","color":"blue","kind":"normal","box":[533,600,553,623],"text":"0","type":"instruction","class":"traffic_sign"},{"light_count":"4","box":[398,468,440,490],"attribute":[{"red":"off","green":"on","x_light":"off","others_arrow":"off","yellow":"off","left_arrow":"off"}],"type":"car","class":"traffic_light","direction":"horizontal"},{"light_count":"4","box":[484,488,524,509],"attribute":[{"red":"off","green":"on","x_light":"off","others_arrow":"off","yellow":"off","left_arrow":"off"}],"type":"car","class":"traffic_light","direction":"horizontal"}],"image":{"filename":"14803951.jpg","imsize":[1920,1080]}}