{"annotation":[{"shape":"circle","color":"blue","kind":"normal","box":[1319,468,1400,556],"text":"0","type":"instruction","class":"traffic_sign"},{"shape":"rectangle","color":"blue","kind":"normal","box":[1390,547,1410,569],"text":"0","type":"instruction","class":"traffic_sign"},{"light_count":"3","box":[977,104,1080,138],"attribute":[{"red":"on","green":"off","x_light":"off","others_arrow":"off","yellow":"off","left_arrow":"off"}],"type":"car","class":"traffic_light","direction":"horizontal"},{"light_count":"3","box":[444,332,496,351],"attribute":[{"red":"on","green":"off","x_light":"off","others_arrow":"off","yellow":"off","left_arrow":"off"}],"type":"car","class":"traffic_light","direction":"horizontal"},{"light_count":"3","box":[1698,110,1784,152],"attribute":[{"red":"off","green":"on","x_light":"off","others_arrow":"off","yellow":"off","left_arrow":"off"}],"type":"car","class":"traffic_light","direction":"horizontal"}],"image":{"filename":"14986314.jpg","imsize":[1920,1080]}}