{"annotation":[{"shape":"circle","color":"blue","kind":"normal","box":[850,314,879,354],"text":"0","type":"instruction","class":"traffic_sign"},{"shape":"circle","color":"blue","kind":"normal","box":[1807,81,1863,162],"text":"0","type":"instruction","class":"traffic_sign"},{"shape":"circle","color":"red","kind":"normal","box":[1045,460,1063,481],"text":"0","type":"restriction","class":"traffic_sign"},{"light_count":"3","box":[738,334,796,359],"attribute":[{"red":"on","green":"off","x_light":"off","others_arrow":"off","yellow":"off","left_arrow":"off"}],"type":"car","class":"traffic_light","direction":"horizontal"},{"light_count":"3","box":[886,338,942,359],"attribute":[{"red":"on","green":"off","x_light":"off","others_arrow":"off","yellow":"off","left_arrow":"off"}],"type":"car","class":"traffic_light","direction":"horizontal"},{"light_count":"3","box":[1701,154,1778,195],"attribute":[{"red":"off","green":"on","x_light":"off","others_arrow":"off","yellow":"off","left_arrow":"off"}],"type":"car","class":"traffic_light","direction":"horizontal"},{"light_count":"3","box":[1877,113,1920,155],"attribute":[{"red":"off","green":"on","x_light":"off","others_arrow":"off","yellow":"off","left_arrow":"off"}],"type":"car","class":"traffic_light","direction":"horizontal"},{"light_count":"2","box":[1802,419,1831,487],"attribute":[{"red":"on","green":"off","x_light":"off","others_arrow":"off","yellow":"off","left_arrow":"off"}],"type":"pedestrian","class":"traffic_light","direction":"vertical"},{"light_count":"2","box":[228,439,262,503],"attribute":[{"red":"on","green":"off","x_light":"off","others_arrow":"off","yellow":"off","left_arrow":"off"}],"type":"pedestrian","class":"traffic_light","direction":"vertical"},{"light_count":"2","box":[1077,453,1091,500],"attribute":[{"red":"off","green":"off","x_light":"off","others_arrow":"off","yellow":"off","left_arrow":"off"}],"type":"pedestrian","class":"traffic_light","direction":"vertical"},{"light_count":"3","box":[1077,397,1090,447],"attribute":[{"red":"off","green":"off","x_light":"off","others_arrow":"off","yellow":"off","left_arrow":"off"}],"type":"car","class":"traffic_light","direction":"vertical"}],"image":{"filename":"15457587.jpg","imsize":[1920,1080]}}