{"annotation":[{"shape":"rectangle","color":"blue","kind":"normal","box":[876,394,893,420],"text":"0","type":"instruction","class":"traffic_sign"},{"shape":"circle","color":"red","kind":"normal","box":[1039,422,1055,442],"text":"0","type":"restriction","class":"traffic_sign"},{"shape":"triangle","color":"yellow","kind":"normal","box":[925,440,938,451],"text":"0","type":"caution","class":"traffic_sign"},{"light_count":"3","box":[869,385,895,396],"attribute":[{"red":"on","green":"off","x_light":"off","others_arrow":"off","yellow":"off","left_arrow":"off"}],"type":"car","class":"traffic_light","direction":"horizontal"},{"light_count":"3","box":[939,383,967,394],"attribute":[{"red":"off","green":"on","x_light":"off","others_arrow":"off","yellow":"off","left_arrow":"off"}],"type":"car","class":"traffic_light","direction":"horizontal"},{"light_count":"3","box":[913,423,923,429],"attribute":[{"red":"on","green":"off","x_light":"off","others_arrow":"off","yellow":"off","left_arrow":"off"}],"type":"car","class":"traffic_light","direction":"horizontal"}],"image":{"filename":"15739676.jpg","imsize":[1920,1080]}}