{"annotation":[{"shape":"circle","color":"red","kind":"normal","box":[485,333,503,352],"text":"30","type":"restriction","class":"traffic_sign"},{"shape":"circle","color":"red","kind":"normal","box":[620,338,638,357],"text":"30","type":"restriction","class":"traffic_sign"},{"shape":"circle","color":"red","kind":"normal","box":[750,347,768,366],"text":"5","type":"restriction","class":"traffic_sign"},{"shape":"circle","color":"blue","kind":"normal","box":[663,321,685,346],"text":"0","type":"instruction","class":"traffic_sign"},{"light_count":"1","box":[670,262,683,276],"attribute":[{"red":"off","green":"off","x_light":"off","others_arrow":"on","yellow":"off","left_arrow":"off"}],"type":"car","class":"traffic_light","direction":"horizontal"},{"light_count":"1","box":[561,258,574,273],"attribute":[{"red":"off","green":"off","x_light":"off","others_arrow":"off","yellow":"off","left_arrow":"off"}],"type":"car","class":"traffic_light","direction":"horizontal"},{"box":[488,359,502,374],"class":"traffic_sign"}],"image":{"filename":"s01030754.jpg","imsize":[1280,720]}}