{"annotation":[{"light_count":"4","box":[695,214,718,221],"attribute":[{"red":"on","green":"off","x_light":"off","others_arrow":"off","yellow":"off","left_arrow":"off"}],"type":"car","class":"traffic_light","direction":"horizontal"},{"light_count":"4","box":[649,215,674,221],"attribute":[{"red":"on","green":"off","x_light":"off","others_arrow":"off","yellow":"off","left_arrow":"off"}],"type":"car","class":"traffic_light","direction":"horizontal"},{"shape":"circle","color":"blue","kind":"normal","box":[638,203,650,215],"text":"0","type":"instruction","class":"traffic_sign"},{"light_count":"4","box":[606,216,629,221],"attribute":[{"red":"on","green":"off","x_light":"off","others_arrow":"off","yellow":"off","left_arrow":"off"}],"type":"car","class":"traffic_light","direction":"horizontal"}],"image":{"filename":"s01229274.jpg","imsize":[1280,720]}}