{"annotation":[{"shape":"circle","color":"blue","kind":"normal","box":[202,182,256,241],"text":"0","type":"instruction","class":"traffic_sign"},{"shape":"circle","color":"blue","kind":"normal","box":[956,309,977,332],"text":"0","type":"instruction","class":"traffic_sign"},{"shape":"circle","color":"red","kind":"normal","box":[791,276,809,293],"text":"01","type":"restriction","class":"traffic_sign"},{"light_count":"3","box":[168,194,195,272],"attribute":[{"red":"off","green":"off","x_light":"off","others_arrow":"off","yellow":"off","left_arrow":"off"}],"type":"car","class":"traffic_light","direction":"vertical"},{"light_count":"4","box":[680,279,710,290],"attribute":[{"red":"off","green":"off","x_light":"off","others_arrow":"off","yellow":"off","left_arrow":"off"}],"type":"car","class":"traffic_light","direction":"horizontal"},{"light_count":"4","box":[740,281,769,293],"attribute":[{"red":"off","green":"off","x_light":"off","others_arrow":"off","yellow":"off","left_arrow":"off"}],"type":"car","class":"traffic_light","direction":"horizontal"},{"light_count":"2","box":[466,335,476,353],"attribute":[{"red":"off","green":"off","x_light":"off","others_arrow":"off","yellow":"off","left_arrow":"off"}],"type":"pedestrian","class":"traffic_light","direction":"vertical"}],"image":{"filename":"s01446467.jpg","imsize":[1280,720]}}