{"annotation":[{"shape":"triangle","color":"blue","kind":"normal","box":[1121,455,1137,471],"text":"0","type":"instruction","class":"traffic_sign"},{"shape":"triangle","color":"blue","kind":"normal","box":[1132,478,1150,491],"text":"0","type":"instruction","class":"traffic_sign"},{"shape":"rectangle","color":"blue","kind":"normal","box":[1016,523,1026,535],"text":"0","type":"instruction","class":"traffic_sign"},{"light_count":"3","box":[1006,489,1024,496],"attribute":[{"red":"on","green":"off","x_light":"off","others_arrow":"off","yellow":"off","left_arrow":"off"}],"type":"car","class":"traffic_light","direction":"horizontal"},{"box":[1064,488,1083,496],"attribute":[{"red":"off","green":"off","x_light":"off","others_arrow":"off","yellow":"off","left_arrow":"off"}],"type":"car","class":"traffic_light","direction":"horizontal","light_count":"unknown"}],"image":{"filename":"s01560953.jpg","imsize":[1920,1200]}}