{"annotation":[{"light_count":"3","box":[1100,394,1146,407],"attribute":[{"red":"off","green":"off","x_light":"off","others_arrow":"off","yellow":"off","left_arrow":"off"}],"type":"car","class":"traffic_light","direction":"horizontal"},{"light_count":"3","box":[948,389,991,406],"attribute":[{"red":"off","green":"off","x_light":"off","others_arrow":"off","yellow":"off","left_arrow":"off"}],"type":"car","class":"traffic_light","direction":"horizontal"}],"image":{"filename":"s01630066.jpg","imsize":[1920,1200]}}